Workbook

Sheet Assumptions
A1: LUCRA — Financial Model Assumptions
A2: Blue cells = editable inputs | All projections in USD
A4: PRICING
B5: Research Tier | C5: Pro Tier
A6: Monthly subscription price ($/mo) | B6: 25 | C6: 59
A7: Annual subscription ($/yr, ~20% discount) | B7: 240 | C7: 564
A9: USER GROWTH (paying subscribers, end of year)
B10: Year 1 | C10: Year 2 | D10: Year 3
A11: Research tier subscribers (EOP) | B11: 200 | C11: 3000 | D11: 12000
A12: Pro tier subscribers (EOP) | B12: 50 | C12: 1000 | D12: 4000
A13: % of users on annual plan (blended) | B13: 0.2 | C13: 0.3 | D13: 0.4
A14: Monthly churn rate | B14: 0.05 | C14: 0.04 | D14: 0.03
A16: VARIABLE COSTS (API cost per user per month)
B17: Research Tier | C17: Pro Tier
A18: Anthropic (Claude Sonnet+Haiku) cost ($/user/mo) | B18: 8 | C18: 15
A19: Data APIs (Finnhub, Perplexity) cost ($/user/mo) | B19: 2 | C19: 4
A20: Total variable COGS ($/user/mo) | B20: =B18+B19 -> 10 | C20: =C18+C19 -> 19
A22: FIXED COSTS (per month)
A23: Infrastructure (Vercel Pro, Firebase Blaze) ($/mo) | B23: 150
A24: Data API base/floor fees (Finnhub paid) ($/mo) | B24: 100
A25: Legal / compliance / insurance ($/mo) | B25: 200
A26: Marketing / content / tools ($/mo) | B26: 500
A27: Founder salary / draw ($/mo) | B27: 0
A29: HIRING PLAN
A30: Month first hire starts (back-end engineer) | B30: 10
A31: Fully-loaded cost — first hire ($/mo) | B31: 12000
A32: Month second hire starts (growth/marketing) | B32: 18
A33: Fully-loaded cost — second hire ($/mo) | B33: 10000

Sheet Monthly P&L
A1: LUCRA — Monthly P&L (36-Month Projection)
B2: Year 1 | N2: Year 2 | Z2: Year 3
A3: ($USD) | B3: Jan | C3: Feb | D3: Mar | E3: Apr | F3: May | G3: Jun | H3: Jul | I3: Aug | J3: Sep | K3: Oct | L3: Nov | M3: Dec | N3: Jan | O3: Feb | P3: Mar | Q3: Apr | R3: May | S3: Jun | T3: Jul | U3: Aug | V3: Sep | W3: Oct | X3: Nov | Y3: Dec | Z3: Jan | AA3: Feb | AB3: Mar | AC3: Apr | AD3: May | AE3: Jun | AF3: Jul | AG3: Aug | AH3: Sep | AI3: Oct | AJ3: Nov | AK3: Dec
A5: SUBSCRIBERS
A6: Research tier subscribers (avg during month) | B6: 0 | C6: 0 | D6: 0 | E6: 67 | F6: 83 | G6: 100 | H6: 117 | I6: 133 | J6: 150 | K6: 167 | L6: 183 | M6: 200 | N6: 433 | O6: 667 | P6: 900 | Q6: 1133 | R6: 1367 | S6: 1600 | T6: 1833 | U6: 2067 | V6: 2300 | W6: 2533 | X6: 2767 | Y6: 3000 | Z6: 3750 | AA6: 4500 | AB6: 5250 | AC6: 6000 | AD6: 6750 | AE6: 7500 | AF6: 8250 | AG6: 9000 | AH6: 9750 | AI6: 10500 | AJ6: 11250 | AK6: 12000
A7: Pro tier subscribers (avg during month) | B7: 0 | C7: 0 | D7: 0 | E7: 17 | F7: 21 | G7: 25 | H7: 29 | I7: 33 | J7: 38 | K7: 42 | L7: 46 | M7: 50 | N7: 129 | O7: 208 | P7: 288 | Q7: 367 | R7: 446 | S7: 525 | T7: 604 | U7: 683 | V7: 762 | W7: 842 | X7: 921 | Y7: 1000 | Z7: 1250 | AA7: 1500 | AB7: 1750 | AC7: 2000 | AD7: 2250 | AE7: 2500 | AF7: 2750 | AG7: 3000 | AH7: 3250 | AI7: 3500 | AJ7: 3750 | AK7: 4000
A8: Total paying subscribers | B8: =B6+B7 -> 0 | C8: =C6+C7 -> 0 | D8: =D6+D7 -> 0 | E8: =E6+E7 -> 84 | F8: =F6+F7 -> 104 | G8: =G6+G7 -> 125 | H8: =H6+H7 -> 146 | I8: =I6+I7 -> 166 | ... AK8: =AK6+AK7 -> 16000
A10: REVENUE
A11: Research tier MRR | B11: =B6*Assumptions!B6 -> 0 | C11: =C6*Assumptions!B6 -> 0 | D11: =D6*Assumptions!B6 -> 0 | E11: =E6*Assumptions!B6 -> 1675 | F11: =F6*Assumptions!B6 -> 2075 | G11: =G6*Assumptions!B6 -> 2500 | H11: =H6*Assumptions!B6 -> 2925 | I11: =I6*Assumptions!B6 -> 3325 | J11: =J6*Assumptions!B6 -> 3750 | K11: =K6*Assumptions!B6 -> 4175 | L11: =L6*Assumptions!B6 -> 4575 | M11: =M6*Assumptions!B6 -> 5000 | N11: =N6*Assumptions!B6 -> 10825 | O11: =O6*Assumptions!B6 -> 16675 | P11: =P6*Assumptions!B6 -> 22500 | Q11: =Q6*Assumptions!B6 -> 28325 | R11: =R6*Assumptions!B6 -> 34175 | S11: =S6*Assumptions!B6 -> 40000 | T11: =T6*Assumptions!B6 -> 45825 | U11: =U6*Assumptions!B6 -> 51675 | V11: =V6*Assumptions!B6 -> 57500 | W11: =W6*Assumptions!B6 -> 63325 | X11: =X6*Assumptions!B6 -> 69175 | Y11: =Y6*Assumptions!B6 -> 75000 | Z11: =Z6*Assumptions!B6 -> 93750 | AA11: =AA6*Assumptions!B6 -> 112500 | AB11: =AB6*Assumptions!B6 -> 131250 | AC11: =AC6*Assumptions!B6 -> 150000 | AD11: =AD6*Assumptions!B6 -> 168750 | AE11: =AE6*Assumptions!B6 -> 187500 | AF11: =AF6*Assumptions!B6 -> 206250 | AG11: =AG6*Assumptions!B6 -> 225000 | AH11: =AH6*Assumptions!B6 -> 243750 | AI11: =AI6*Assumptions!B6 -> 262500 | AJ11: =AJ6*Assumptions!B6 -> 281250 | AK11: =AK6*Assumptions!B6 -> 300000
A12: Pro tier MRR | B12: =B7*Assumptions!C6 -> 0 | C12: =C7*Assumptions!C6 -> 0 | D12: =D7*Assumptions!C6 -> 0 | E12: =E7*Assumptions!C6 -> 1003 | F12: =F7*Assumptions!C6 -> 1239 | G12: =G7*Assumptions!C6 -> 1475 | H12: =H7*Assumptions!C6 -> 1711 | I12: =I7*Assumptions!C6 -> 1947 | J12: =J7*Assumptions!C6 -> 2242 | K12: =K7*Assumptions!C6 -> 2478 | L12: =L7*Assumptions!C6 -> 2714 | M12: =M7*Assumptions!C6 -> 2950 | N12: =N7*Assumptions!C6 -> 7611 | O12: =O7*Assumptions!C6 -> 12272 | P12: =P7*Assumptions!C6 -> 16992 | Q12: =Q7*Assumptions!C6 -> 21653 | R12: =R7*Assumptions!C6 -> 26314 | S12: =S7*Assumptions!C6 -> 30975 | T12: =T7*Assumptions!C6 -> 35636 | U12: =U7*Assumptions!C6 -> 40297 | V12: =V7*Assumptions!C6 -> 44958 | W12: =W7*Assumptions!C6 -> 49678 | X12: =X7*Assumptions!C6 -> 54339 | Y12: =Y7*Assumptions!C6 -> 59000 | Z12: =Z7*Assumptions!C6 -> 73750 | AA12: =AA7*Assumptions!C6 -> 88500 | AB12: =AB7*Assumptions!C6 -> 103250 | AC12: =AC7*Assumptions!C6 -> 118000 | AD12: =AD7*Assumptions!C6 -> 132750 | AE12: =AE7*Assumptions!C6 -> 147500 | AF12: =AF7*Assumptions!C6 -> 162250 | AG12: =AG7*Assumptions!C6 -> 177000 | AH12: =AH7*Assumptions!C6 -> 191750 | AI12: =AI7*Assumptions!C6 -> 206500 | AJ12: =AJ7*Assumptions!C6 -> 221250 | AK12: =AK7*Assumptions!C6 -> 236000
A13: Total MRR | B13: =B11+B12 -> 0 | C13: =C11+C12 -> 0 | D13: =D11+D12 -> 0 | E13: =E11+E12 -> 2678 | F13: =F11+F12 -> 3314 | G13: =G11+G12 -> 3975 | H13: =H11+H12 -> 4636 | I13: =I11+I12 -> 5272 | ... AK13: =AK11+AK12 -> 536000
A14: Total ARR (annualised) | B14: =B13*12 -> 0 | C14: =C13*12 -> 0 | D14: =D13*12 -> 0 | E14: =E13*12 -> 32136 | F14: =F13*12 -> 39768 | G14: =G13*12 -> 47700 | H14: =H13*12 -> 55632 | I14: =I13*12 -> 63264 | ... AK14: =AK13*12 -> 6432000
A16: VARIABLE COSTS (COGS)
A17: Research tier API costs | B17: =B6*Assumptions!B20 -> 0 | C17: =C6*Assumptions!B20 -> 0 | D17: =D6*Assumptions!B20 -> 0 | E17: =E6*Assumptions!B20 -> 670 | F17: =F6*Assumptions!B20 -> 830 | G17: =G6*Assumptions!B20 -> 1000 | H17: =H6*Assumptions!B20 -> 1170 | I17: =I6*Assumptions!B20 -> 1330 | J17: =J6*Assumptions!B20 -> 1500 | K17: =K6*Assumptions!B20 -> 1670 | L17: =L6*Assumptions!B20 -> 1830 | M17: =M6*Assumptions!B20 -> 2000 | N17: =N6*Assumptions!B20 -> 4330 | O17: =O6*Assumptions!B20 -> 6670 | P17: =P6*Assumptions!B20 -> 9000 | Q17: =Q6*Assumptions!B20 -> 11330 | R17: =R6*Assumptions!B20 -> 13670 | S17: =S6*Assumptions!B20 -> 16000 | T17: =T6*Assumptions!B20 -> 18330 | U17: =U6*Assumptions!B20 -> 20670 | V17: =V6*Assumptions!B20 -> 23000 | W17: =W6*Assumptions!B20 -> 25330 | X17: =X6*Assumptions!B20 -> 27670 | Y17: =Y6*Assumptions!B20 -> 30000 | Z17: =Z6*Assumptions!B20 -> 37500 | AA17: =AA6*Assumptions!B20 -> 45000 | AB17: =AB6*Assumptions!B20 -> 52500 | AC17: =AC6*Assumptions!B20 -> 60000 | AD17: =AD6*Assumptions!B20 -> 67500 | AE17: =AE6*Assumptions!B20 -> 75000 | AF17: =AF6*Assumptions!B20 -> 82500 | AG17: =AG6*Assumptions!B20 -> 90000 | AH17: =AH6*Assumptions!B20 -> 97500 | AI17: =AI6*Assumptions!B20 -> 105000 | AJ17: =AJ6*Assumptions!B20 -> 112500 | AK17: =AK6*Assumptions!B20 -> 120000
A18: Pro tier API costs | B18: =B7*Assumptions!C20 -> 0 | C18: =C7*Assumptions!C20 -> 0 | D18: =D7*Assumptions!C20 -> 0 | E18: =E7*Assumptions!C20 -> 323 | F18: =F7*Assumptions!C20 -> 399 | G18: =G7*Assumptions!C20 -> 475 | H18: =H7*Assumptions!C20 -> 551 | I18: =I7*Assumptions!C20 -> 627 | J18: =J7*Assumptions!C20 -> 722 | K18: =K7*Assumptions!C20 -> 798 | L18: =L7*Assumptions!C20 -> 874 | M18: =M7*Assumptions!C20 -> 950 | N18: =N7*Assumptions!C20 -> 2451 | O18: =O7*Assumptions!C20 -> 3952 | P18: =P7*Assumptions!C20 -> 5472 | Q18: =Q7*Assumptions!C20 -> 6973 | R18: =R7*Assumptions!C20 -> 8474 | S18: =S7*Assumptions!C20 -> 9975 | T18: =T7*Assumptions!C20 -> 11476 | U18: =U7*Assumptions!C20 -> 12977 | V18: =V7*Assumptions!C20 -> 14478 | W18: =W7*Assumptions!C20 -> 15998 | X18: =X7*Assumptions!C20 -> 17499 | Y18: =Y7*Assumptions!C20 -> 19000 | Z18: =Z7*Assumptions!C20 -> 23750 | AA18: =AA7*Assumptions!C20 -> 28500 | AB18: =AB7*Assumptions!C20 -> 33250 | AC18: =AC7*Assumptions!C20 -> 38000 | AD18: =AD7*Assumptions!C20 -> 42750 | AE18: =AE7*Assumptions!C20 -> 47500 | AF18: =AF7*Assumptions!C20 -> 52250 | AG18: =AG7*Assumptions!C20 -> 57000 | AH18: =AH7*Assumptions!C20 -> 61750 | AI18: =AI7*Assumptions!C20 -> 66500 | AJ18: =AJ7*Assumptions!C20 -> 71250 | AK18: =AK7*Assumptions!C20 -> 76000
A19: Total variable COGS | B19: =B17+B18 -> 0 | C19: =C17+C18 -> 0 | D19: =D17+D18 -> 0 | E19: =E17+E18 -> 993 | F19: =F17+F18 -> 1229 | G19: =G17+G18 -> 1475 | H19: =H17+H18 -> 1721 | I19: =I17+I18 -> 1957 | ... AK19: =AK17+AK18 -> 196000
A20: Gross profit | B20: =B13-B19 -> 0 | C20: =C13-C19 -> 0 | D20: =D13-D19 -> 0 | E20: =E13-E19 -> 1685 | F20: =F13-F19 -> 2085 | G20: =G13-G19 -> 2500 | H20: =H13-H19 -> 2915 | I20: =I13-I19 -> 3315 | ... AK20: =AK13-AK19 -> 340000
A21: Gross margin % | B21: =IF(B13=0,0,B20/B13) -> 0 | C21: =IF(C13=0,0,C20/C13) -> 0 | D21: =IF(D13=0,0,D20/D13) -> 0 | E21: =IF(E13=0,0,E20/E13) -> 0.6292009 | F21: =IF(F13=0,0,F20/F13) -> 0.62914906 | G21: =IF(G13=0,0,G20/G13) -> 0.62893082 | H21: =IF(H13=0,0,H20/H13) -> 0.62877481 | I21: =IF(I13=0,0,I20/I13) -> 0.62879363 | ... AK21: =IF(AK13=0,0,AK20/AK13) -> 0.63432836
A23: FIXED OPERATING EXPENSES
A24: Infrastructure & hosting | B24: =Assumptions!B23 -> 150 | C24: =Assumptions!B23 -> 150 | D24: =Assumptions!B23 -> 150 | E24: =Assumptions!B23 -> 150 | F24: =Assumptions!B23 -> 150 | G24: =Assumptions!B23 -> 150 | H24: =Assumptions!B23 -> 150 | I24: =Assumptions!B23 -> 150 | J24: =Assumptions!B23 -> 150 | K24: =Assumptions!B23 -> 150 | L24: =Assumptions!B23 -> 150 | M24: =Assumptions!B23 -> 150 | N24: =Assumptions!B23 -> 150 | O24: =Assumptions!B23 -> 150 | P24: =Assumptions!B23 -> 150 | Q24: =Assumptions!B23 -> 150 | R24: =Assumptions!B23 -> 150 | S24: =Assumptions!B23 -> 150 | T24: =Assumptions!B23 -> 150 | U24: =Assumptions!B23 -> 150 | V24: =Assumptions!B23 -> 150 | W24: =Assumptions!B23 -> 150 | X24: =Assumptions!B23 -> 150 | Y24: =Assumptions!B23 -> 150 | Z24: =Assumptions!B23 -> 150 | AA24: =Assumptions!B23 -> 150 | AB24: =Assumptions!B23 -> 150 | AC24: =Assumptions!B23 -> 150 | AD24: =Assumptions!B23 -> 150 | AE24: =Assumptions!B23 -> 150 | AF24: =Assumptions!B23 -> 150 | AG24: =Assumptions!B23 -> 150 | AH24: =Assumptions!B23 -> 150 | AI24: =Assumptions!B23 -> 150 | AJ24: =Assumptions!B23 -> 150 | AK24: =Assumptions!B23 -> 150
A25: Data API base fees | B25: =Assumptions!B24 -> 100 | C25: =Assumptions!B24 -> 100 | D25: =Assumptions!B24 -> 100 | E25: =Assumptions!B24 -> 100 | F25: =Assumptions!B24 -> 100 | G25: =Assumptions!B24 -> 100 | H25: =Assumptions!B24 -> 100 | I25: =Assumptions!B24 -> 100 | J25: =Assumptions!B24 -> 100 | K25: =Assumptions!B24 -> 100 | L25: =Assumptions!B24 -> 100 | M25: =Assumptions!B24 -> 100 | N25: =Assumptions!B24 -> 100 | O25: =Assumptions!B24 -> 100 | P25: =Assumptions!B24 -> 100 | Q25: =Assumptions!B24 -> 100 | R25: =Assumptions!B24 -> 100 | S25: =Assumptions!B24 -> 100 | T25: =Assumptions!B24 -> 100 | U25: =Assumptions!B24 -> 100 | V25: =Assumptions!B24 -> 100 | W25: =Assumptions!B24 -> 100 | X25: =Assumptions!B24 -> 100 | Y25: =Assumptions!B24 -> 100 | Z25: =Assumptions!B24 -> 100 | AA25: =Assumptions!B24 -> 100 | AB25: =Assumptions!B24 -> 100 | AC25: =Assumptions!B24 -> 100 | AD25: =Assumptions!B24 -> 100 | AE25: =Assumptions!B24 -> 100 | AF25: =Assumptions!B24 -> 100 | AG25: =Assumptions!B24 -> 100 | AH25: =Assumptions!B24 -> 100 | AI25: =Assumptions!B24 -> 100 | AJ25: =Assumptions!B24 -> 100 | AK25: =Assumptions!B24 -> 100
A26: Legal / compliance | B26: =Assumptions!B25 -> 200 | C26: =Assumptions!B25 -> 200 | D26: =Assumptions!B25 -> 200 | E26: =Assumptions!B25 -> 200 | F26: =Assumptions!B25 -> 200 | G26: =Assumptions!B25 -> 200 | H26: =Assumptions!B25 -> 200 | I26: =Assumptions!B25 -> 200 | J26: =Assumptions!B25 -> 200 | K26: =Assumptions!B25 -> 200 | L26: =Assumptions!B25 -> 200 | M26: =Assumptions!B25 -> 200 | N26: =Assumptions!B25 -> 200 | O26: =Assumptions!B25 -> 200 | P26: =Assumptions!B25 -> 200 | Q26: =Assumptions!B25 -> 200 | R26: =Assumptions!B25 -> 200 | S26: =Assumptions!B25 -> 200 | T26: =Assumptions!B25 -> 200 | U26: =Assumptions!B25 -> 200 | V26: =Assumptions!B25 -> 200 | W26: =Assumptions!B25 -> 200 | X26: =Assumptions!B25 -> 200 | Y26: =Assumptions!B25 -> 200 | Z26: =Assumptions!B25 -> 200 | AA26: =Assumptions!B25 -> 200 | AB26: =Assumptions!B25 -> 200 | AC26: =Assumptions!B25 -> 200 | AD26: =Assumptions!B25 -> 200 | AE26: =Assumptions!B25 -> 200 | AF26: =Assumptions!B25 -> 200 | AG26: =Assumptions!B25 -> 200 | AH26: =Assumptions!B25 -> 200 | AI26: =Assumptions!B25 -> 200 | AJ26: =Assumptions!B25 -> 200 | AK26: =Assumptions!B25 -> 200
A27: Marketing & content | B27: =Assumptions!B26 -> 500 | C27: =Assumptions!B26 -> 500 | D27: =Assumptions!B26 -> 500 | E27: =Assumptions!B26 -> 500 | F27: =Assumptions!B26 -> 500 | G27: =Assumptions!B26 -> 500 | H27: =Assumptions!B26 -> 500 | I27: =Assumptions!B26 -> 500 | J27: =Assumptions!B26 -> 500 | K27: =Assumptions!B26 -> 500 | L27: =Assumptions!B26 -> 500 | M27: =Assumptions!B26 -> 500 | N27: =Assumptions!B26 -> 500 | O27: =Assumptions!B26 -> 500 | P27: =Assumptions!B26 -> 500 | Q27: =Assumptions!B26 -> 500 | R27: =Assumptions!B26 -> 500 | S27: =Assumptions!B26 -> 500 | T27: =Assumptions!B26 -> 500 | U27: =Assumptions!B26 -> 500 | V27: =Assumptions!B26 -> 500 | W27: =Assumptions!B26 -> 500 | X27: =Assumptions!B26 -> 500 | Y27: =Assumptions!B26 -> 500 | Z27: =Assumptions!B26 -> 500 | AA27: =Assumptions!B26 -> 500 | AB27: =Assumptions!B26 -> 500 | AC27: =Assumptions!B26 -> 500 | AD27: =Assumptions!B26 -> 500 | AE27: =Assumptions!B26 -> 500 | AF27: =Assumptions!B26 -> 500 | AG27: =Assumptions!B26 -> 500 | AH27: =Assumptions!B26 -> 500 | AI27: =Assumptions!B26 -> 500 | AJ27: =Assumptions!B26 -> 500 | AK27: =Assumptions!B26 -> 500
A28: Personnel (founder + hires) | B28: =Assumptions!B27+IF(1>=Assumptions!B30,Assumptions!B31,0)+IF(1>=Assumptions!B32,Assumptions!B33,0) -> 0 | C28: =Assumptions!B27+IF(2>=Assumptions!B30,Assumptions!B31,0)+IF(2>=Assumptions!B32,Assumptions!B33,0) -> 0 | D28: =Assumptions!B27+IF(3>=Assumptions!B30,Assumptions!B31,0)+IF(3>=Assumptions!B32,Assumptions!B33,0) -> 0 | E28: =Assumptions!B27+IF(4>=Assumptions!B30,Assumptions!B31,0)+IF(4>=Assumptions!B32,Assumptions!B33,0) -> 0 | F28: =Assumptions!B27+IF(5>=Assumptions!B30,Assumptions!B31,0)+IF(5>=Assumptions!B32,Assumptions!B33,0) -> 0 | G28: =Assumptions!B27+IF(6>=Assumptions!B30,Assumptions!B31,0)+IF(6>=Assumptions!B32,Assumptions!B33,0) -> 0 | H28: =Assumptions!B27+IF(7>=Assumptions!B30,Assumptions!B31,0)+IF(7>=Assumptions!B32,Assumptions!B33,0) -> 0 | I28: =Assumptions!B27+IF(8>=Assumptions!B30,Assumptions!B31,0)+IF(8>=Assumptions!B32,Assumptions!B33,0) -> 0 | J28: =Assumptions!B27+IF(9>=Assumptions!B30,Assumptions!B31,0)+IF(9>=Assumptions!B32,Assumptions!B33,0) -> 0 | K28: =Assumptions!B27+IF(10>=Assumptions!B30,Assumptions!B31,0)+IF(10>=Assumptions!B32,Assumptions!B33,0) -> 12000 | L28: =Assumptions!B27+IF(11>=Assumptions!B30,Assumptions!B31,0)+IF(11>=Assumptions!B32,Assumptions!B33,0) -> 12000 | M28: =Assumptions!B27+IF(12>=Assumptions!B30,Assumptions!B31,0)+IF(12>=Assumptions!B32,Assumptions!B33,0) -> 12000 | N28: =Assumptions!B27+IF(13>=Assumptions!B30,Assumptions!B31,0)+IF(13>=Assumptions!B32,Assumptions!B33,0) -> 12000 | O28: =Assumptions!B27+IF(14>=Assumptions!B30,Assumptions!B31,0)+IF(14>=Assumptions!B32,Assumptions!B33,0) -> 12000 | P28: =Assumptions!B27+IF(15>=Assumptions!B30,Assumptions!B31,0)+IF(15>=Assumptions!B32,Assumptions!B33,0) -> 12000 | Q28: =Assumptions!B27+IF(16>=Assumptions!B30,Assumptions!B31,0)+IF(16>=Assumptions!B32,Assumptions!B33,0) -> 12000 | R28: =Assumptions!B27+IF(17>=Assumptions!B30,Assumptions!B31,0)+IF(17>=Assumptions!B32,Assumptions!B33,0) -> 12000 | S28: =Assumptions!B27+IF(18>=Assumptions!B30,Assumptions!B31,0)+IF(18>=Assumptions!B32,Assumptions!B33,0) -> 22000 | T28: =Assumptions!B27+IF(19>=Assumptions!B30,Assumptions!B31,0)+IF(19>=Assumptions!B32,Assumptions!B33,0) -> 22000 | U28: =Assumptions!B27+IF(20>=Assumptions!B30,Assumptions!B31,0)+IF(20>=Assumptions!B32,Assumptions!B33,0) -> 22000 | V28: =Assumptions!B27+IF(21>=Assumptions!B30,Assumptions!B31,0)+IF(21>=Assumptions!B32,Assumptions!B33,0) -> 22000 | W28: =Assumptions!B27+IF(22>=Assumptions!B30,Assumptions!B31,0)+IF(22>=Assumptions!B32,Assumptions!B33,0) -> 22000 | X28: =Assumptions!B27+IF(23>=Assumptions!B30,Assumptions!B31,0)+IF(23>=Assumptions!B32,Assumptions!B33,0) -> 22000 | Y28: =Assumptions!B27+IF(24>=Assumptions!B30,Assumptions!B31,0)+IF(24>=Assumptions!B32,Assumptions!B33,0) -> 22000 | Z28: =Assumptions!B27+IF(25>=Assumptions!B30,Assumptions!B31,0)+IF(25>=Assumptions!B32,Assumptions!B33,0) -> 22000 | AA28: =Assumptions!B27+IF(26>=Assumptions!B30,Assumptions!B31,0)+IF(26>=Assumptions!B32,Assumptions!B33,0) -> 22000 | AB28: =Assumptions!B27+IF(27>=Assumptions!B30,Assumptions!B31,0)+IF(27>=Assumptions!B32,Assumptions!B33,0) -> 22000 | AC28: =Assumptions!B27+IF(28>=Assumptions!B30,Assumptions!B31,0)+IF(28>=Assumptions!B32,Assumptions!B33,0) -> 22000 | AD28: =Assumptions!B27+IF(29>=Assumptions!B30,Assumptions!B31,0)+IF(29>=Assumptions!B32,Assumptions!B33,0) -> 22000 | AE28: =Assumptions!B27+IF(30>=Assumptions!B30,Assumptions!B31,0)+IF(30>=Assumptions!B32,Assumptions!B33,0) -> 22000 | AF28: =Assumptions!B27+IF(31>=Assumptions!B30,Assumptions!B31,0)+IF(31>=Assumptions!B32,Assumptions!B33,0) -> 22000 | AG28: =Assumptions!B27+IF(32>=Assumptions!B30,Assumptions!B31,0)+IF(32>=Assumptions!B32,Assumptions!B33,0) -> 22000 | AH28: =Assumptions!B27+IF(33>=Assumptions!B30,Assumptions!B31,0)+IF(33>=Assumptions!B32,Assumptions!B33,0) -> 22000 | AI28: =Assumptions!B27+IF(34>=Assumptions!B30,Assumptions!B31,0)+IF(34>=Assumptions!B32,Assumptions!B33,0) -> 22000 | AJ28: =Assumptions!B27+IF(35>=Assumptions!B30,Assumptions!B31,0)+IF(35>=Assumptions!B32,Assumptions!B33,0) -> 22000 | AK28: =Assumptions!B27+IF(36>=Assumptions!B30,Assumptions!B31,0)+IF(36>=Assumptions!B32,Assumptions!B33,0) -> 22000
A29: Total fixed OpEx | B29: =SUM(B24:B28) -> 950 | C29: =SUM(C24:C28) -> 950 | D29: =SUM(D24:D28) -> 950 | E29: =SUM(E24:E28) -> 950 | F29: =SUM(F24:F28) -> 950 | G29: =SUM(G24:G28) -> 950 | H29: =SUM(H24:H28) -> 950 | I29: =SUM(I24:I28) -> 950 | ... AK29: =SUM(AK24:AK28) -> 22950
A31: BOTTOM LINE
A32: EBITDA | B32: =B20-B29 -> -950 | C32: =C20-C29 -> -950 | D32: =D20-D29 -> -950 | E32: =E20-E29 -> 735 | F32: =F20-F29 -> 1135 | G32: =G20-G29 -> 1550 | H32: =H20-H29 -> 1965 | I32: =I20-I29 -> 2365 | ... AK32: =AK20-AK29 -> 317050
A33: EBITDA margin % | B33: =IF(B13=0,0,B32/B13) -> 0 | C33: =IF(C13=0,0,C32/C13) -> 0 | D33: =IF(D13=0,0,D32/D13) -> 0 | E33: =IF(E13=0,0,E32/E13) -> 0.27445855 | F33: =IF(F13=0,0,F32/F13) -> 0.34248642 | G33: =IF(G13=0,0,G32/G13) -> 0.38993711 | H33: =IF(H13=0,0,H32/H13) -> 0.42385677 | I33: =IF(I13=0,0,I32/I13) -> 0.44859636 | ... AK33: =IF(AK13=0,0,AK32/AK13) -> 0.59151119
A34: Cumulative cash position | B34: =B32 -> -950 | C34: =B34+C32 -> -1900 | D34: =C34+D32 -> -2850 | E34: =D34+E32 -> -2115 | F34: =E34+F32 -> -980 | G34: =F34+G32 -> 570 | H34: =G34+H32 -> 2535 | I34: =H34+I32 -> 4900 | J34: =I34+J32 -> 7720 | ... AK34: =AJ34+AK32 -> 2739340

Sheet Annual Summary
A1: LUCRA — Annual Summary
B3: Year 1 | C3: Year 2 | D3: Year 3
A4: SUBSCRIBERS (end of year)
A5: Research tier (EOP) | B5: ='Monthly P&L'!M6 -> 200 | C5: ='Monthly P&L'!Y6 -> 3000 | D5: ='Monthly P&L'!AK6 -> 12000
A6: Pro tier (EOP) | B6: ='Monthly P&L'!M7 -> 50 | C6: ='Monthly P&L'!Y7 -> 1000 | D6: ='Monthly P&L'!AK7 -> 4000
A7: Total paying subscribers (EOP) | B7: ='Monthly P&L'!M8 -> 250 | C7: ='Monthly P&L'!Y8 -> 4000 | D7: ='Monthly P&L'!AK8 -> 16000
A9: REVENUE
A10: Total revenue (full year) | B10: =SUM('Monthly P&L'!B13:M13) -> 47759 | C10: =SUM('Monthly P&L'!N13:Y13) -> 914725 | D10: =SUM('Monthly P&L'!Z13:AK13) -> 4221000
A11: ARR at year-end (annualised MRR) | B11: ='Monthly P&L'!M14 -> 95400 | C11: ='Monthly P&L'!Y14 -> 1608000 | D11: ='Monthly P&L'!AK14 -> 6432000
A12: Revenue growth YoY | B12: — | C12: =IF(B10=0,0,(C10-B10)/B10) -> 18.152935 | D12: =IF(C10=0,0,(D10-C10)/C10) -> 3.6145016
A14: PROFITABILITY
A15: Gross profit (full year) | B15: =SUM('Monthly P&L'!B20:M20) -> 30040 | C15: =SUM('Monthly P&L'!N20:Y20) -> 580000 | D15: =SUM('Monthly P&L'!Z20:AK20) -> 2677500
A16: Gross margin % | B16: =IF(B10=0,0,B15/B10) -> 0.62899139 | C16: =IF(C10=0,0,C15/C10) -> 0.63407035 | D16: =IF(D10=0,0,D15/D10) -> 0.63432836
A17: Total fixed OpEx (full year) | B17: =SUM('Monthly P&L'!B29:M29) -> 47400 | C17: =SUM('Monthly P&L'!N29:Y29) -> 225400 | D17: =SUM('Monthly P&L'!Z29:AK29) -> 275400
A18: EBITDA (full year) | B18: =SUM('Monthly P&L'!B32:M32) -> -17360 | C18: =SUM('Monthly P&L'!N32:Y32) -> 354600 | D18: =SUM('Monthly P&L'!Z32:AK32) -> 2402100
A19: EBITDA margin % | B19: =IF(B10=0,0,B18/B10) -> -0.3634917 | C19: =IF(C10=0,0,C18/C10) -> 0.38765749 | D19: =IF(D10=0,0,D18/D10) -> 0.56908316
A21: UNIT ECONOMICS
A22: Blended CAC estimate ($) | B22: 80 | C22: 65 | D22: 50
A23: Blended ARPU/month | B23: =IF(B7=0,0,B10/(MAX(B7,1)*12)) -> 15.919667 | C23: =IF(C7=0,0,C10/(MAX(C7,1)*12)) -> 19.056771 | D23: =IF(D7=0,0,D10/(MAX(D7,1)*12)) -> 21.984375
A24: Implied LTV (12mo, 70% retention) | B24: =B23*12*0.7 -> 133.7252 | C24: =C23*12*0.7 -> 160.07688 | D24: =D23*12*0.7 -> 184.66875
A25: LTV:CAC ratio | B25: =IF(B22=0,0,B24/B22) -> 1.671565 | C25: =IF(C22=0,0,C24/C22) -> 2.4627212 | D25: =IF(D22=0,0,D24/D22) -> 3.693375
A26: CAC payback period (months) | B26: =IF(B23=0,0,B22/B23) -> 5.0252308 | C26: =IF(C23=0,0,C22/C23) -> 3.4108612 | D26: =IF(D23=0,0,D22/D23) -> 2.2743426
A28: CASH POSITION (cumulative)
A29: Cumulative cash (end of year) | B29: ='Monthly P&L'!M34 -> -17360 | C29: ='Monthly P&L'!Y34 -> 337240 | D29: ='Monthly P&L'!AK34 -> 2739340

Sheet Unit Economics
A1: LUCRA — Unit Economics Deep Dive
B3: Research Tier | C3: Pro Tier | D3: Blended
A4: REVENUE PER USER
A5: Monthly price ($/mo) | B5: =Assumptions!B6 -> 25 | C5: =Assumptions!C6 -> 59 | D5: =(B5+C5)/2 -> 42
A6: Annual price ($/yr) | B6: =Assumptions!B7 -> 240 | C6: =Assumptions!C7 -> 564 | D6: =(B6+C6)/2 -> 402
A8: VARIABLE COST PER USER / MONTH
A9: Anthropic API cost | B9: =Assumptions!B18 -> 8 | C9: =Assumptions!C18 -> 15 | D9: =(B9+C9)/2 -> 11.5
A10: Data API cost | B10: =Assumptions!B19 -> 2 | C10: =Assumptions!C19 -> 4 | D10: =(B10+C10)/2 -> 3
A11: Total variable COGS | B11: =B9+B10 -> 10 | C11: =C9+C10 -> 19 | D11: =D9+D10 -> 14.5
A13: MONTHLY UNIT ECONOMICS
A14: Monthly contribution margin | B14: =B5-B11 -> 15 | C14: =C5-C11 -> 40 | D14: =D5-D11 -> 27.5
A15: Contribution margin % | B15: =B14/B5 -> 0.6 | C15: =C14/C5 -> 0.6779661 | D15: =D14/D5 -> 0.6547619
A17: PAYBACK & LTV (at current churn assumptions)
A18: Assumed blended CAC ($) | B18: 80 | C18: 120 | D18: 95
A19: Monthly churn rate | B19: =Assumptions!B14 -> 0.05 | C19: =Assumptions!B14 -> 0.05 | D19: =Assumptions!B14 -> 0.05
A20: Avg customer lifetime (months) | B20: =ROUND(1/B19,1) -> 20 | C20: =ROUND(1/C19,1) -> 20 | D20: =ROUND(1/D19,1) -> 20
A21: LTV (contribution margin × lifetime) | B21: =B14*B20 -> 300 | C21: =C14*C20 -> 800 | D21: =D14*D20 -> 550
A22: LTV:CAC ratio | B22: =B21/B18 -> 3.75 | C22: =C21/C18 -> 6.6666667 | D22: =D21/D18 -> 5.7894737
A23: CAC payback period (months) | B23: =ROUND(B18/B14,1) -> 5.3 | C23: =ROUND(C18/C14,1) -> 3 | D23: =ROUND(D18/D14,1) -> 3.5
A25: API COST SENSITIVITY (queries per month)
A26: Cost per query at plan limit (30 queries) | B26: =B11/30 -> 0.33333333 | C26: =C11/30 -> 0.63333333 | D26: =D11/30 -> 0.48333333
A27: Max profitable queries at current price | B27: =FLOOR(B5/B26,1) -> 75 | C27: =FLOOR(C5/C26,1) -> 93 | D27: =FLOOR(D5/D26,1) -> 86
A28: Revenue per query at plan limit | B28: =B5/30 -> 0.83333333 | C28: =C5/30 -> 1.9666667 | D28: =D5/30 -> 1.4
A29: Gross margin per query | B29: =B28-B26 -> 0.5 | C29: =C28-C26 -> 1.3333333 | D29: =D28-D26 -> 0.91666667
